Streamlit_menu/__init__.py
Streamlit_menu/main.py
Streamlit_menu/multipage.py
Streamlit_menu/st_menu/__init__.py
Streamlit_menu/st_menu/register.py
st_menu_component-1.1.0.dist-info/METADATA
st_menu_component-1.1.0.dist-info/WHEEL
st_menu_component-1.1.0.dist-info/top_level.txt
st_menu_component-1.1.0.dist-info/RECORD
