Metadata-Version: 2.1
Name: st-menu-component
Version: 1.1.0
Summary: Customizable menu component for the streamlit developes
Home-page: 
Author: Subhash Jadhav
Author-email: subhash.jadhav@bluepineapple.io
Requires-Python: >=3.6
Requires-Dist: altair (==4.2.0)
Requires-Dist: aniso8601 (==9.0.1)
Requires-Dist: appdirs (==1.4.4)
Requires-Dist: attrs (==22.1.0)
Requires-Dist: blinker (==1.5)
Requires-Dist: cachetools (==5.2.0)
Requires-Dist: certifi (==2022.6.15)
Requires-Dist: cffi (==1.15.1)
Requires-Dist: charset-normalizer (==2.1.1)
Requires-Dist: click (==8.1.3)
Requires-Dist: colorama (==0.4.5)
Requires-Dist: commonmark (==0.9.1)
Requires-Dist: cryptography (==38.0.1)
Requires-Dist: decorator (==5.1.1)
Requires-Dist: docopt (==0.6.2)
Requires-Dist: entrypoints (==0.4)
Requires-Dist: ez-setup (==0.9)
Requires-Dist: Flask (==2.2.2)
Requires-Dist: Flask-API (==3.0.post1)
Requires-Dist: Flask-Cors (==3.0.10)
Requires-Dist: Flask-RESTful (==0.3.9)
Requires-Dist: Flask-SQLAlchemy (==2.5.1)
Requires-Dist: gitdb (==4.0.10)
Requires-Dist: GitPython (==3.1.29)
Requires-Dist: greenlet (==1.1.3)
Requires-Dist: idna (==3.3)
Requires-Dist: importlib-metadata (==5.1.0)
Requires-Dist: itsdangerous (==2.1.2)
Requires-Dist: Jinja2 (==3.1.2)
Requires-Dist: jsonschema (==4.17.3)
Requires-Dist: jwt (==1.3.1)
Requires-Dist: lxml (==4.9.1)
Requires-Dist: MarkupSafe (==2.1.1)
Requires-Dist: multitasking (==0.0.11)
Requires-Dist: mysql-connector-python (==8.0.31)
Requires-Dist: numpy (==1.23.5)
Requires-Dist: packaging (==21.3)
Requires-Dist: pandas (==1.5.2)
Requires-Dist: Pillow (==9.3.0)
Requires-Dist: pipreqs (==0.4.11)
Requires-Dist: protobuf (==3.20.1)
Requires-Dist: pyarrow (==10.0.1)
Requires-Dist: pycparser (==2.21)
Requires-Dist: pydeck (==0.8.0)
Requires-Dist: Pygments (==2.13.0)
Requires-Dist: PyJWT (==2.4.0)
Requires-Dist: Pympler (==1.0.1)
Requires-Dist: pyparsing (==3.0.9)
Requires-Dist: pyrsistent (==0.19.2)
Requires-Dist: python-dateutil (==2.8.2)
Requires-Dist: pytz (==2022.2.1)
Requires-Dist: pytz-deprecation-shim (==0.1.0.post0)
Requires-Dist: requests (==2.28.1)
Requires-Dist: rich (==12.6.0)
Requires-Dist: semver (==2.13.0)
Requires-Dist: six (==1.16.0)
Requires-Dist: smmap (==5.0.0)
Requires-Dist: SQLAlchemy (==1.4.41)
Requires-Dist: streamlit (==1.15.1)
Requires-Dist: toml (==0.10.2)
Requires-Dist: toolz (==0.12.0)
Requires-Dist: tornado (==6.2)
Requires-Dist: typing-extensions (==4.4.0)
Requires-Dist: tzdata (==2022.7)
Requires-Dist: tzlocal (==4.2)
Requires-Dist: urllib3 (==1.26.12)
Requires-Dist: validators (==0.20.0)
Requires-Dist: watchdog (==2.1.9)
Requires-Dist: Werkzeug (==2.2.2)
Requires-Dist: yarg (==0.1.9)
Requires-Dist: yfinance (==0.1.87)
Requires-Dist: zipp (==3.11.0)
